[
  {
    "id": 1,
    "name": "CODHAB",
    "staff_id": 1375,
    "legal_advice_id": 8,
    "created_at": "2015-04-17T15:14:54.213-03:00",
    "updated_at": "2016-10-07T10:49:30.697-03:00"
  },
  {
    "id": 2,
    "name": "CODHAB",
    "staff_id": 1375,
    "legal_advice_id": 8,
    "created_at": "2015-04-17T15:14:58.377-03:00",
    "updated_at": "2016-10-07T10:49:30.764-03:00"
  },
  {
    "id": 3,
    "name": "Partido dos Trabalhadores PT",
    "staff_id": 1375,
    "legal_advice_id": 8,
    "created_at": "2015-04-17T15:15:12.777-03:00",
    "updated_at": "2016-10-07T10:49:30.774-03:00"
  },
  {
    "id": 4,
    "name": "CODHAB",
    "staff_id": 1375,
    "legal_advice_id": 9,
    "created_at": "2015-04-22T08:31:51.117-03:00",
    "updated_at": "2016-10-07T10:49:30.783-03:00"
  },
  {
    "id": 5,
    "name": "Projebel Serviços Comércio LTDA",
    "staff_id": 1375,
    "legal_advice_id": 9,
    "created_at": "2015-04-22T08:32:13.953-03:00",
    "updated_at": "2016-10-07T10:49:30.792-03:00"
  },
  {
    "id": 6,
    "name": "CODHAB",
    "staff_id": 1375,
    "legal_advice_id": 11,
    "created_at": "2015-04-22T15:57:01.153-03:00",
    "updated_at": "2016-10-07T10:49:30.799-03:00"
  },
  {
    "id": 7,
    "name": "Projebel Serviços Comércio LTDA",
    "staff_id": 1375,
    "legal_advice_id": 11,
    "created_at": "2015-04-22T15:57:08.873-03:00",
    "updated_at": "2016-10-07T10:49:30.805-03:00"
  },
  {
    "id": 8,
    "name": "CODHAB",
    "staff_id": 1375,
    "legal_advice_id": 15,
    "created_at": "2015-04-24T16:15:45.927-03:00",
    "updated_at": "2016-10-07T10:49:30.814-03:00"
  },
  {
    "id": 9,
    "name": "Jardins Mangueiral Empreendimentos Imobiliários ",
    "staff_id": 1375,
    "legal_advice_id": 15,
    "created_at": "2015-04-24T16:16:11.277-03:00",
    "updated_at": "2016-10-07T10:49:30.822-03:00"
  },
  {
    "id": 10,
    "name": "Condomínio Jardins do Pequis",
    "staff_id": 1375,
    "legal_advice_id": 15,
    "created_at": "2015-04-24T16:16:36.517-03:00",
    "updated_at": "2016-10-07T10:49:30.836-03:00"
  },
  {
    "id": 11,
    "name": "Jardins Mangueiral Empreendimentos Imobiliários ",
    "staff_id": 1375,
    "legal_advice_id": 18,
    "created_at": "2015-04-29T17:02:08.487-03:00",
    "updated_at": "2016-10-07T10:49:30.846-03:00"
  },
  {
    "id": 12,
    "name": "Associação Pro Morar do Movimento Vida de Samambaia AMMVS",
    "staff_id": 1375,
    "legal_advice_id": 19,
    "created_at": "2015-04-30T16:26:29.170-03:00",
    "updated_at": "2016-10-07T10:49:30.856-03:00"
  },
  {
    "id": 13,
    "name": "Associação Pro Morar do Movimento Vida de Samambaia AMMVS",
    "staff_id": 1375,
    "legal_advice_id": 19,
    "created_at": "2015-04-30T16:26:48.217-03:00",
    "updated_at": "2016-10-07T10:49:30.868-03:00"
  },
  {
    "id": 14,
    "name": "CODHAB",
    "staff_id": 1375,
    "legal_advice_id": 19,
    "created_at": "2015-04-30T16:27:00.400-03:00",
    "updated_at": "2016-10-07T10:49:30.879-03:00"
  },
  {
    "id": 15,
    "name": "CODHAB",
    "staff_id": 1375,
    "legal_advice_id": 20,
    "created_at": "2015-05-04T13:56:11.363-03:00",
    "updated_at": "2016-10-07T10:49:30.889-03:00"
  },
  {
    "id": 16,
    "name": "Projebel Serviços Comércio LTDA",
    "staff_id": 1375,
    "legal_advice_id": 20,
    "created_at": "2015-05-04T13:56:17.307-03:00",
    "updated_at": "2016-10-07T10:49:30.898-03:00"
  },
  {
    "id": 17,
    "name": "CODHAB",
    "staff_id": 1375,
    "legal_advice_id": 21,
    "created_at": "2015-05-04T15:09:47.807-03:00",
    "updated_at": "2016-10-07T10:49:30.907-03:00"
  },
  {
    "id": 18,
    "name": "CODHAB",
    "staff_id": 1375,
    "legal_advice_id": 23,
    "created_at": "2015-05-06T17:46:17.413-03:00",
    "updated_at": "2016-10-07T10:49:30.917-03:00"
  },
  {
    "id": 19,
    "name": "Projebel Serviços Comércio LTDA",
    "staff_id": 1375,
    "legal_advice_id": 23,
    "created_at": "2015-05-06T17:46:25.307-03:00",
    "updated_at": "2016-10-07T10:49:30.928-03:00"
  },
  {
    "id": 20,
    "name": "CODHAB",
    "staff_id": 1375,
    "legal_advice_id": 37,
    "created_at": "2015-05-19T15:59:23.147-03:00",
    "updated_at": "2016-10-07T10:49:30.937-03:00"
  },
  {
    "id": 21,
    "name": "Associação dos Pioneiros Moradores e Inquilinos da Candangolândia",
    "staff_id": 1375,
    "legal_advice_id": 37,
    "created_at": "2015-05-19T15:59:49.357-03:00",
    "updated_at": "2016-10-07T10:49:30.948-03:00"
  },
  {
    "id": 22,
    "name": "Rodrigo Leal Ribeiro",
    "staff_id": 1375,
    "legal_advice_id": 65,
    "created_at": "2015-05-20T16:17:35.557-03:00",
    "updated_at": "2016-10-07T10:49:30.961-03:00"
  },
  {
    "id": 23,
    "name": "Iguaciane de Lima Neves",
    "staff_id": 1375,
    "legal_advice_id": 65,
    "created_at": "2015-05-20T16:17:56.883-03:00",
    "updated_at": "2016-10-07T10:49:30.974-03:00"
  },
  {
    "id": 24,
    "name": "Rosilda Rodrigues dos Santos",
    "staff_id": 1375,
    "legal_advice_id": 67,
    "created_at": "2015-05-25T14:15:57.993-03:00",
    "updated_at": "2016-10-07T10:49:30.985-03:00"
  },
  {
    "id": 25,
    "name": "Jorge Rodrigues Pereira",
    "staff_id": 1375,
    "legal_advice_id": 67,
    "created_at": "2015-05-25T14:16:22.140-03:00",
    "updated_at": "2016-10-07T10:49:31.000-03:00"
  },
  {
    "id": 26,
    "name": "Terracap",
    "staff_id": 1375,
    "legal_advice_id": 39,
    "created_at": "2015-05-26T14:18:06.003-03:00",
    "updated_at": "2016-10-07T10:49:31.012-03:00"
  },
  {
    "id": 27,
    "name": "Maria Rodrigues Vieira",
    "staff_id": 1375,
    "legal_advice_id": 39,
    "created_at": "2015-05-26T14:18:22.927-03:00",
    "updated_at": "2016-10-07T10:49:31.023-03:00"
  },
  {
    "id": 28,
    "name": "Adelia Maria da Aparecida",
    "staff_id": 1375,
    "legal_advice_id": 39,
    "created_at": "2015-05-26T14:18:34.300-03:00",
    "updated_at": "2016-10-07T10:49:31.237-03:00"
  },
  {
    "id": 29,
    "name": "Izaneide Vieira Rodrigues",
    "staff_id": 1375,
    "legal_advice_id": 39,
    "created_at": "2015-05-26T14:18:45.923-03:00",
    "updated_at": "2016-10-07T10:49:31.247-03:00"
  },
  {
    "id": 30,
    "name": "Edilson Rodrigues Vieira",
    "staff_id": 1375,
    "legal_advice_id": 39,
    "created_at": "2015-05-26T14:19:03.147-03:00",
    "updated_at": "2016-10-07T10:49:31.260-03:00"
  },
  {
    "id": 31,
    "name": "Maria de Fátima Moura",
    "staff_id": 1375,
    "legal_advice_id": 40,
    "created_at": "2015-05-27T13:38:53.813-03:00",
    "updated_at": "2016-10-07T10:49:31.272-03:00"
  },
  {
    "id": 32,
    "name": "Paulo de Jesus Neri",
    "staff_id": 1375,
    "legal_advice_id": 40,
    "created_at": "2015-05-27T13:39:12.250-03:00",
    "updated_at": "2016-10-07T10:49:31.280-03:00"
  },
  {
    "id": 33,
    "name": "CODHAB",
    "staff_id": 1375,
    "legal_advice_id": 42,
    "created_at": "2015-05-28T16:18:16.203-03:00",
    "updated_at": "2016-10-07T10:49:31.286-03:00"
  },
  {
    "id": 34,
    "name": "CODHAB",
    "staff_id": 1375,
    "legal_advice_id": 44,
    "created_at": "2015-05-28T16:44:13.143-03:00",
    "updated_at": "2016-10-07T10:49:31.293-03:00"
  },
  {
    "id": 35,
    "name": "CODHAB",
    "staff_id": 1375,
    "legal_advice_id": 45,
    "created_at": "2015-05-29T11:00:17.037-03:00",
    "updated_at": "2016-10-07T10:49:31.302-03:00"
  },
  {
    "id": 36,
    "name": "Projebel Serviços Comércio LTDA",
    "staff_id": 1375,
    "legal_advice_id": 45,
    "created_at": "2015-05-29T11:00:28.410-03:00",
    "updated_at": "2016-10-07T10:49:31.310-03:00"
  },
  {
    "id": 37,
    "name": "CODHAB",
    "staff_id": 1375,
    "legal_advice_id": 3642,
    "created_at": "2015-05-29T11:07:49.013-03:00",
    "updated_at": "2016-10-07T10:49:31.319-03:00"
  },
  {
    "id": 38,
    "name": "Jardins Mangueiral Empreendimentos Imobiliários ",
    "staff_id": 1375,
    "legal_advice_id": 3642,
    "created_at": "2015-05-29T11:08:00.543-03:00",
    "updated_at": "2016-10-07T10:49:31.326-03:00"
  },
  {
    "id": 39,
    "name": "Distrito Federal",
    "staff_id": 1375,
    "legal_advice_id": 3642,
    "created_at": "2015-05-29T11:08:11.120-03:00",
    "updated_at": "2016-10-07T10:49:31.334-03:00"
  },
  {
    "id": 40,
    "name": "CODHAB",
    "staff_id": 1375,
    "legal_advice_id": 5198,
    "created_at": "2015-05-29T11:10:13.423-03:00",
    "updated_at": "2016-10-07T10:49:31.345-03:00"
  },
  {
    "id": 41,
    "name": "CODHAB",
    "staff_id": 1375,
    "legal_advice_id": 47,
    "created_at": "2015-05-29T14:49:17.377-03:00",
    "updated_at": "2016-10-07T10:49:31.356-03:00"
  },
  {
    "id": 42,
    "name": "Governo do Distrito Federal",
    "staff_id": 1375,
    "legal_advice_id": 47,
    "created_at": "2015-05-29T14:49:32.323-03:00",
    "updated_at": "2016-10-07T10:49:31.368-03:00"
  },
  {
    "id": 43,
    "name": "Agencia de Fiscalização do DF",
    "staff_id": 1375,
    "legal_advice_id": 47,
    "created_at": "2015-05-29T14:49:43.463-03:00",
    "updated_at": "2016-10-07T10:49:31.379-03:00"
  },
  {
    "id": 44,
    "name": "CODHAB",
    "staff_id": 1375,
    "legal_advice_id": 48,
    "created_at": "2015-05-29T14:54:06.387-03:00",
    "updated_at": "2016-10-07T10:49:31.388-03:00"
  },
  {
    "id": 45,
    "name": "CODHAB",
    "staff_id": 1375,
    "legal_advice_id": 49,
    "created_at": "2015-05-29T15:06:11.373-03:00",
    "updated_at": "2016-10-07T10:49:31.395-03:00"
  },
  {
    "id": 46,
    "name": "CODHAB",
    "staff_id": 1375,
    "legal_advice_id": 51,
    "created_at": "2015-06-03T10:02:47.117-03:00",
    "updated_at": "2016-10-07T10:49:31.402-03:00"
  },
  {
    "id": 47,
    "name": "Distrito Federal",
    "staff_id": 1375,
    "legal_advice_id": 51,
    "created_at": "2015-06-03T10:02:53.637-03:00",
    "updated_at": "2016-10-07T10:49:31.412-03:00"
  },
  {
    "id": 48,
    "name": "Agencia de Fiscalização do DF",
    "staff_id": 1375,
    "legal_advice_id": 51,
    "created_at": "2015-06-03T10:03:02.623-03:00",
    "updated_at": "2016-10-07T10:49:31.423-03:00"
  },
  {
    "id": 49,
    "name": "Banco de Brasília",
    "staff_id": 1375,
    "legal_advice_id": 53,
    "created_at": "2015-06-03T13:33:38.523-03:00",
    "updated_at": "2016-10-07T10:49:31.436-03:00"
  },
  {
    "id": 50,
    "name": "CODHAB",
    "staff_id": 1375,
    "legal_advice_id": 54,
    "created_at": "2015-06-03T13:45:25.067-03:00",
    "updated_at": "2016-10-07T10:49:31.448-03:00"
  },
  {
    "id": 51,
    "name": "Rogerio Rodrigues de Souza",
    "staff_id": 1375,
    "legal_advice_id": 56,
    "created_at": "2015-06-08T08:59:50.250-03:00",
    "updated_at": "2016-10-07T10:49:31.462-03:00"
  },
  {
    "id": 52,
    "name": "codhab",
    "staff_id": 521,
    "legal_advice_id": 36,
    "created_at": "2015-06-08T11:27:30.280-03:00",
    "updated_at": "2016-10-07T10:49:31.475-03:00"
  },
  {
    "id": 53,
    "name": "CODHAB",
    "staff_id": 1375,
    "legal_advice_id": 57,
    "created_at": "2015-06-08T13:37:27.223-03:00",
    "updated_at": "2016-10-07T10:49:31.486-03:00"
  },
  {
    "id": 54,
    "name": "Projebel Serviços Comércio LTDA",
    "staff_id": 1375,
    "legal_advice_id": 57,
    "created_at": "2015-06-08T13:37:37.503-03:00",
    "updated_at": "2016-10-07T10:49:31.494-03:00"
  },
  {
    "id": 55,
    "name": "Partido dos Trabalhadores PT",
    "staff_id": 1375,
    "legal_advice_id": 57,
    "created_at": "2015-06-08T13:37:47.143-03:00",
    "updated_at": "2016-10-07T10:49:31.505-03:00"
  },
  {
    "id": 56,
    "name": "CODHAB",
    "staff_id": 1375,
    "legal_advice_id": 58,
    "created_at": "2015-06-08T13:40:06.157-03:00",
    "updated_at": "2016-10-07T10:49:31.512-03:00"
  },
  {
    "id": 57,
    "name": "Projebel Serviços Comércio LTDA",
    "staff_id": 1375,
    "legal_advice_id": 58,
    "created_at": "2015-06-08T13:40:15.080-03:00",
    "updated_at": "2016-10-07T10:49:31.522-03:00"
  },
  {
    "id": 58,
    "name": "Partido dos Trabalhadores PT",
    "staff_id": 1375,
    "legal_advice_id": 58,
    "created_at": "2015-06-08T13:40:23.083-03:00",
    "updated_at": "2016-10-07T10:49:31.532-03:00"
  },
  {
    "id": 59,
    "name": "CODHAB",
    "staff_id": 1375,
    "legal_advice_id": 59,
    "created_at": "2015-06-08T13:42:08.417-03:00",
    "updated_at": "2016-10-07T10:49:31.545-03:00"
  },
  {
    "id": 60,
    "name": "Francenilton de Lima",
    "staff_id": 1375,
    "legal_advice_id": 60,
    "created_at": "2015-06-08T14:13:52.040-03:00",
    "updated_at": "2016-10-07T10:49:31.558-03:00"
  },
  {
    "id": 61,
    "name": "CODHAB",
    "staff_id": 1375,
    "legal_advice_id": 61,
    "created_at": "2015-06-08T14:20:10.783-03:00",
    "updated_at": "2016-10-07T10:49:31.568-03:00"
  },
  {
    "id": 62,
    "name": "Distrito Federal",
    "staff_id": 1375,
    "legal_advice_id": 61,
    "created_at": "2015-06-08T14:20:18.317-03:00",
    "updated_at": "2016-10-07T10:49:31.582-03:00"
  },
  {
    "id": 63,
    "name": "Terracap",
    "staff_id": 1375,
    "legal_advice_id": 61,
    "created_at": "2015-06-08T14:20:25.087-03:00",
    "updated_at": "2016-10-07T10:49:31.591-03:00"
  },
  {
    "id": 64,
    "name": "União Federal",
    "staff_id": 1375,
    "legal_advice_id": 61,
    "created_at": "2015-06-08T14:20:35.273-03:00",
    "updated_at": "2016-10-07T10:49:31.600-03:00"
  },
  {
    "id": 65,
    "name": "Associação Morar Vida de Samambaia",
    "staff_id": 1375,
    "legal_advice_id": 61,
    "created_at": "2015-06-08T14:20:54.510-03:00",
    "updated_at": "2016-10-07T10:49:31.609-03:00"
  },
  {
    "id": 66,
    "name": "Instituto Brasilia Ambiental do GDF",
    "staff_id": 1375,
    "legal_advice_id": 61,
    "created_at": "2015-06-08T14:21:19.517-03:00",
    "updated_at": "2016-10-07T10:49:31.618-03:00"
  },
  {
    "id": 67,
    "name": "Diretor Presidente da CODHAB",
    "staff_id": 1375,
    "legal_advice_id": 62,
    "created_at": "2015-06-09T14:48:04.263-03:00",
    "updated_at": "2016-10-07T10:49:31.625-03:00"
  },
  {
    "id": 68,
    "name": "CODHAB",
    "staff_id": 1375,
    "legal_advice_id": 64,
    "created_at": "2015-06-09T14:55:54.777-03:00",
    "updated_at": "2016-10-07T10:49:31.632-03:00"
  },
  {
    "id": 69,
    "name": "Distrito Federal",
    "staff_id": 1375,
    "legal_advice_id": 68,
    "created_at": "2015-06-10T16:58:51.530-03:00",
    "updated_at": "2016-10-07T10:49:31.638-03:00"
  },
  {
    "id": 70,
    "name": "Francisca Ximenes Meneses de Souza",
    "staff_id": 1375,
    "legal_advice_id": 69,
    "created_at": "2015-06-11T15:43:26.187-03:00",
    "updated_at": "2016-10-07T10:49:31.644-03:00"
  },
  {
    "id": 71,
    "name": "CODHAB",
    "staff_id": 1375,
    "legal_advice_id": 71,
    "created_at": "2015-06-12T15:20:13.110-03:00",
    "updated_at": "2016-10-07T10:49:31.652-03:00"
  },
  {
    "id": 72,
    "name": "Aurea Maria Ferrreira Ervilha",
    "staff_id": 1375,
    "legal_advice_id": 72,
    "created_at": "2015-06-15T18:19:35.210-03:00",
    "updated_at": "2016-10-07T10:49:31.657-03:00"
  },
  {
    "id": 73,
    "name": "Pedro Soares Lustosa",
    "staff_id": 1375,
    "legal_advice_id": 75,
    "created_at": "2015-06-15T18:27:17.847-03:00",
    "updated_at": "2016-10-07T10:49:31.664-03:00"
  },
  {
    "id": 74,
    "name": "CODHAB",
    "staff_id": 521,
    "legal_advice_id": 81,
    "created_at": "2015-06-17T09:26:32.953-03:00",
    "updated_at": "2016-10-07T10:49:31.669-03:00"
  },
  {
    "id": 75,
    "name": "CODHAB",
    "staff_id": 1375,
    "legal_advice_id": 83,
    "created_at": "2015-06-18T15:25:07.123-03:00",
    "updated_at": "2016-10-07T10:49:31.675-03:00"
  },
  {
    "id": 76,
    "name": "Jose Santana de Souza",
    "staff_id": 1375,
    "legal_advice_id": 80,
    "created_at": "2015-06-19T16:26:45.613-03:00",
    "updated_at": "2016-10-07T10:49:31.683-03:00"
  },
  {
    "id": 77,
    "name": "Irias Gomes de Souza",
    "staff_id": 1375,
    "legal_advice_id": 80,
    "created_at": "2015-06-19T16:28:07.747-03:00",
    "updated_at": "2016-10-07T10:49:31.690-03:00"
  },
  {
    "id": 78,
    "name": "CODHAB",
    "staff_id": 1375,
    "legal_advice_id": 87,
    "created_at": "2015-07-03T17:18:19.457-03:00",
    "updated_at": "2016-10-07T10:49:31.696-03:00"
  },
  {
    "id": 79,
    "name": "Agencia de Fiscalização do DF",
    "staff_id": 1375,
    "legal_advice_id": 87,
    "created_at": "2015-07-03T17:18:26.930-03:00",
    "updated_at": "2016-10-07T10:49:31.702-03:00"
  },
  {
    "id": 80,
    "name": "Distrito Federal",
    "staff_id": 1375,
    "legal_advice_id": 87,
    "created_at": "2015-07-03T17:18:36.010-03:00",
    "updated_at": "2016-10-07T10:49:31.710-03:00"
  },
  {
    "id": 81,
    "name": "Wanderley de Oliveira Barreiros e outros",
    "staff_id": 1375,
    "legal_advice_id": 91,
    "created_at": "2015-07-08T16:16:00.450-03:00",
    "updated_at": "2016-10-07T10:49:31.721-03:00"
  },
  {
    "id": 82,
    "name": "CODHAB",
    "staff_id": 1375,
    "legal_advice_id": 92,
    "created_at": "2015-07-08T16:24:21.650-03:00",
    "updated_at": "2016-10-07T10:49:31.729-03:00"
  },
  {
    "id": 83,
    "name": "Marcos Rodrigues Cruciol",
    "staff_id": 1375,
    "legal_advice_id": 92,
    "created_at": "2015-07-08T16:24:38.967-03:00",
    "updated_at": "2016-10-07T10:49:31.740-03:00"
  },
  {
    "id": 84,
    "name": "CODHAB",
    "staff_id": 1375,
    "legal_advice_id": 101,
    "created_at": "2015-07-28T15:44:53.317-03:00",
    "updated_at": "2016-10-07T10:49:31.750-03:00"
  },
  {
    "id": 85,
    "name": "CODHAB",
    "staff_id": 1375,
    "legal_advice_id": 102,
    "created_at": "2015-07-28T15:48:40.283-03:00",
    "updated_at": "2016-10-07T10:49:31.757-03:00"
  },
  {
    "id": 86,
    "name": "Icema Industria de Ceramica Nacional LTDA",
    "staff_id": 1375,
    "legal_advice_id": 106,
    "created_at": "2015-08-03T16:11:52.870-03:00",
    "updated_at": "2016-10-07T10:49:31.764-03:00"
  },
  {
    "id": 87,
    "name": "Edivaldo Albuquerque Martins e outros",
    "staff_id": 1375,
    "legal_advice_id": 108,
    "created_at": "2015-08-05T18:06:12.917-03:00",
    "updated_at": "2016-10-07T10:49:31.773-03:00"
  },
  {
    "id": 88,
    "name": "CODHAB",
    "staff_id": 1375,
    "legal_advice_id": 112,
    "created_at": "2015-08-24T14:48:43.793-03:00",
    "updated_at": "2016-10-07T10:49:31.779-03:00"
  },
  {
    "id": 89,
    "name": "CODHAB",
    "staff_id": 1375,
    "legal_advice_id": 113,
    "created_at": "2015-08-24T14:53:09.493-03:00",
    "updated_at": "2016-10-07T10:49:31.785-03:00"
  },
  {
    "id": 90,
    "name": "CODHAB",
    "staff_id": 1375,
    "legal_advice_id": 114,
    "created_at": "2015-08-24T14:56:56.290-03:00",
    "updated_at": "2016-10-07T10:49:31.795-03:00"
  },
  {
    "id": 91,
    "name": "Priscila Rosa Ramos",
    "staff_id": 1375,
    "legal_advice_id": 115,
    "created_at": "2015-08-25T16:29:16.323-03:00",
    "updated_at": "2016-10-07T10:49:31.799-03:00"
  },
  {
    "id": 92,
    "name": "Maria Pereira Braga",
    "staff_id": 1375,
    "legal_advice_id": 116,
    "created_at": "2015-08-25T16:35:36.293-03:00",
    "updated_at": "2016-10-07T10:49:31.804-03:00"
  },
  {
    "id": 93,
    "name": "CODHAB",
    "staff_id": 1375,
    "legal_advice_id": 117,
    "created_at": "2015-09-03T17:15:14.323-03:00",
    "updated_at": "2016-10-07T10:49:31.808-03:00"
  },
  {
    "id": 94,
    "name": "Diretor Presidente da CODHAB",
    "staff_id": 1375,
    "legal_advice_id": 119,
    "created_at": "2015-09-08T17:22:24.043-03:00",
    "updated_at": "2016-10-07T10:49:31.813-03:00"
  },
  {
    "id": 95,
    "name": "CODHAB",
    "staff_id": 1375,
    "legal_advice_id": 120,
    "created_at": "2015-09-10T17:55:59.483-03:00",
    "updated_at": "2016-10-07T10:49:31.818-03:00"
  },
  {
    "id": 96,
    "name": "CODHAB",
    "staff_id": 1375,
    "legal_advice_id": 123,
    "created_at": "2015-09-14T17:56:18.020-03:00",
    "updated_at": "2016-10-07T10:49:31.826-03:00"
  },
  {
    "id": 97,
    "name": "CODHAB",
    "staff_id": 1375,
    "legal_advice_id": 124,
    "created_at": "2015-09-14T17:58:49.840-03:00",
    "updated_at": "2016-10-07T10:49:31.830-03:00"
  },
  {
    "id": 98,
    "name": "CODHAB",
    "staff_id": 1375,
    "legal_advice_id": 134,
    "created_at": "2015-09-15T18:14:20.023-03:00",
    "updated_at": "2016-10-07T10:49:31.834-03:00"
  },
  {
    "id": 99,
    "name": "Gevanildo Mozart Soares",
    "staff_id": 1375,
    "legal_advice_id": 125,
    "created_at": "2015-09-16T16:20:19.287-03:00",
    "updated_at": "2016-10-07T10:49:31.852-03:00"
  },
  {
    "id": 100,
    "name": "Edilamar Lopes Soares",
    "staff_id": 1375,
    "legal_advice_id": 125,
    "created_at": "2015-09-16T16:20:39.757-03:00",
    "updated_at": "2016-10-07T10:49:31.860-03:00"
  },
  {
    "id": 101,
    "name": "Horaci Gomes Abadia",
    "staff_id": 1375,
    "legal_advice_id": 125,
    "created_at": "2015-09-16T16:20:51.407-03:00",
    "updated_at": "2016-10-07T10:49:31.867-03:00"
  },
  {
    "id": 102,
    "name": "Maria de Fatima Cavalcante de Oliveira",
    "staff_id": 1375,
    "legal_advice_id": 126,
    "created_at": "2015-09-16T16:34:16.877-03:00",
    "updated_at": "2016-10-07T10:49:31.874-03:00"
  },
  {
    "id": 103,
    "name": "CODHAB",
    "staff_id": 1375,
    "legal_advice_id": 141,
    "created_at": "2015-09-30T18:12:22.123-03:00",
    "updated_at": "2016-10-07T10:49:31.879-03:00"
  },
  {
    "id": 104,
    "name": "Jardins Mangueiral Empreendimentos Imobiliários",
    "staff_id": 1375,
    "legal_advice_id": 141,
    "created_at": "2015-09-30T18:12:44.930-03:00",
    "updated_at": "2016-10-07T10:49:31.884-03:00"
  },
  {
    "id": 105,
    "name": "CODHAB",
    "staff_id": 1375,
    "legal_advice_id": 143,
    "created_at": "2015-10-01T18:05:47.250-03:00",
    "updated_at": "2016-10-07T10:49:31.889-03:00"
  },
  {
    "id": 106,
    "name": "Cícero Londerry Batista",
    "staff_id": 1375,
    "legal_advice_id": 143,
    "created_at": "2015-10-01T18:06:02.227-03:00",
    "updated_at": "2016-10-07T10:49:31.893-03:00"
  },
  {
    "id": 107,
    "name": "Eduardo Idelfonso de Melo ",
    "staff_id": 1375,
    "legal_advice_id": 151,
    "created_at": "2015-10-07T17:18:29.453-03:00",
    "updated_at": "2016-10-07T10:49:32.103-03:00"
  },
  {
    "id": 108,
    "name": "Antonio Cezar Batista Meireles",
    "staff_id": 1375,
    "legal_advice_id": 154,
    "created_at": "2015-10-08T17:45:12.107-03:00",
    "updated_at": "2016-10-07T10:49:32.119-03:00"
  },
  {
    "id": 109,
    "name": "CODHAB",
    "staff_id": 1375,
    "legal_advice_id": 155,
    "created_at": "2015-10-08T17:48:05.987-03:00",
    "updated_at": "2016-10-07T10:49:32.132-03:00"
  },
  {
    "id": 110,
    "name": "Antonia pontes Pereira",
    "staff_id": 1375,
    "legal_advice_id": 155,
    "created_at": "2015-10-08T17:48:23.723-03:00",
    "updated_at": "2016-10-07T10:49:32.142-03:00"
  },
  {
    "id": 111,
    "name": "Luciano Nobrega Queiroga",
    "staff_id": 1375,
    "legal_advice_id": 156,
    "created_at": "2015-10-14T18:02:07.897-03:00",
    "updated_at": "2016-10-07T10:49:32.151-03:00"
  },
  {
    "id": 112,
    "name": "CODHAB",
    "staff_id": 1375,
    "legal_advice_id": 157,
    "created_at": "2015-10-14T18:12:57.427-03:00",
    "updated_at": "2016-10-07T10:49:32.161-03:00"
  },
  {
    "id": 113,
    "name": "CODHAB",
    "staff_id": 1375,
    "legal_advice_id": 158,
    "created_at": "2015-10-14T18:15:40.307-03:00",
    "updated_at": "2016-10-07T10:49:32.168-03:00"
  },
  {
    "id": 114,
    "name": "CODHAB",
    "staff_id": 1375,
    "legal_advice_id": 159,
    "created_at": "2015-10-14T18:17:59.057-03:00",
    "updated_at": "2016-10-07T10:49:32.175-03:00"
  },
  {
    "id": 115,
    "name": "CODHAB",
    "staff_id": 1375,
    "legal_advice_id": 160,
    "created_at": "2015-10-14T18:22:40.200-03:00",
    "updated_at": "2016-10-07T10:49:32.180-03:00"
  },
  {
    "id": 116,
    "name": "CODHAB",
    "staff_id": 1375,
    "legal_advice_id": 161,
    "created_at": "2015-10-14T18:24:59.947-03:00",
    "updated_at": "2016-10-07T10:49:32.185-03:00"
  },
  {
    "id": 117,
    "name": "CODHAB",
    "staff_id": 1375,
    "legal_advice_id": 162,
    "created_at": "2015-10-14T18:27:17.230-03:00",
    "updated_at": "2016-10-07T10:49:32.192-03:00"
  },
  {
    "id": 118,
    "name": "CODHAB",
    "staff_id": 1375,
    "legal_advice_id": 163,
    "created_at": "2015-10-14T18:29:41.000-03:00",
    "updated_at": "2016-10-07T10:49:32.198-03:00"
  },
  {
    "id": 119,
    "name": "CODHAB",
    "staff_id": 1375,
    "legal_advice_id": 164,
    "created_at": "2015-10-14T18:35:05.390-03:00",
    "updated_at": "2016-10-07T10:49:32.204-03:00"
  },
  {
    "id": 120,
    "name": "WILLIAM CAVALCANTE DE OLIVEIRA",
    "staff_id": 514,
    "legal_advice_id": 214,
    "created_at": "2016-02-01T16:19:55.403-02:00",
    "updated_at": "2016-10-07T10:49:32.209-03:00"
  },
  {
    "id": 121,
    "name": "CODHAB",
    "staff_id": 514,
    "legal_advice_id": 220,
    "created_at": "2016-02-11T14:42:35.160-02:00",
    "updated_at": "2016-10-07T10:49:32.214-03:00"
  },
  {
    "id": 122,
    "name": "CODHAB",
    "staff_id": 514,
    "legal_advice_id": 230,
    "created_at": "2016-02-22T13:55:18.607-03:00",
    "updated_at": "2016-10-07T10:49:32.220-03:00"
  },
  {
    "id": 123,
    "name": "CODHAB",
    "staff_id": 514,
    "legal_advice_id": 450,
    "created_at": "2016-07-11T16:00:10.803-03:00",
    "updated_at": "2016-10-07T10:49:32.225-03:00"
  },
  {
    "id": 124,
    "name": "CODHAB",
    "staff_id": 514,
    "legal_advice_id": 5657,
    "created_at": "2016-10-18T08:41:37.374-02:00",
    "updated_at": "2016-10-18T08:41:37.374-02:00"
  },
  {
    "id": 125,
    "name": "DF",
    "staff_id": 514,
    "legal_advice_id": 5705,
    "created_at": "2016-11-28T16:08:12.708-02:00",
    "updated_at": "2016-11-28T16:08:12.708-02:00"
  },
  {
    "id": 126,
    "name": "ALBERTO PEREIRA DA SILVA ",
    "staff_id": 1436,
    "legal_advice_id": 5726,
    "created_at": "2017-01-05T10:55:09.062-02:00",
    "updated_at": "2017-01-05T10:55:09.062-02:00"
  },
  {
    "id": 127,
    "name": "EDIVA LOPES DE SOUZA",
    "staff_id": 1436,
    "legal_advice_id": 5728,
    "created_at": "2017-01-12T10:06:14.853-02:00",
    "updated_at": "2017-01-12T10:06:14.853-02:00"
  },
  {
    "id": 128,
    "name": "MANASSES DA SILVA CARDOSO",
    "staff_id": 1436,
    "legal_advice_id": 5729,
    "created_at": "2017-01-12T10:21:01.119-02:00",
    "updated_at": "2017-01-12T10:21:01.119-02:00"
  },
  {
    "id": 129,
    "name": "CODHAB",
    "staff_id": 1436,
    "legal_advice_id": 5730,
    "created_at": "2017-01-12T10:26:55.993-02:00",
    "updated_at": "2017-01-12T10:26:55.993-02:00"
  },
  {
    "id": 130,
    "name": "CODHAB",
    "staff_id": 1436,
    "legal_advice_id": 5731,
    "created_at": "2017-01-12T10:39:17.105-02:00",
    "updated_at": "2017-01-12T10:39:17.105-02:00"
  },
  {
    "id": 131,
    "name": "CODHAB",
    "staff_id": 1436,
    "legal_advice_id": 5731,
    "created_at": "2017-01-12T10:41:29.872-02:00",
    "updated_at": "2017-01-12T10:41:29.872-02:00"
  },
  {
    "id": 132,
    "name": "CODHAB",
    "staff_id": 1436,
    "legal_advice_id": 5732,
    "created_at": "2017-01-12T10:52:17.462-02:00",
    "updated_at": "2017-01-12T10:52:17.462-02:00"
  },
  {
    "id": 133,
    "name": "CODHAB",
    "staff_id": 1436,
    "legal_advice_id": 5733,
    "created_at": "2017-01-12T10:56:48.266-02:00",
    "updated_at": "2017-01-12T10:56:48.266-02:00"
  },
  {
    "id": 134,
    "name": "CODHAB",
    "staff_id": 1436,
    "legal_advice_id": 5734,
    "created_at": "2017-01-12T11:00:32.006-02:00",
    "updated_at": "2017-01-12T11:00:32.006-02:00"
  },
  {
    "id": 135,
    "name": "CODHAB",
    "staff_id": 1436,
    "legal_advice_id": 5735,
    "created_at": "2017-01-12T11:04:32.965-02:00",
    "updated_at": "2017-01-12T11:04:32.965-02:00"
  },
  {
    "id": 136,
    "name": "CODHAB",
    "staff_id": 1436,
    "legal_advice_id": 5736,
    "created_at": "2017-01-12T11:21:07.664-02:00",
    "updated_at": "2017-01-12T11:21:07.664-02:00"
  },
  {
    "id": 137,
    "name": "CODHAB",
    "staff_id": 1436,
    "legal_advice_id": 5737,
    "created_at": "2017-01-12T11:27:24.026-02:00",
    "updated_at": "2017-01-12T11:27:24.026-02:00"
  },
  {
    "id": 138,
    "name": "CODHAB",
    "staff_id": 1436,
    "legal_advice_id": 5738,
    "created_at": "2017-01-12T11:34:55.107-02:00",
    "updated_at": "2017-01-12T11:34:55.107-02:00"
  },
  {
    "id": 139,
    "name": "CODHAB",
    "staff_id": 1436,
    "legal_advice_id": 5739,
    "created_at": "2017-01-16T10:44:50.260-02:00",
    "updated_at": "2017-01-16T10:44:50.260-02:00"
  },
  {
    "id": 140,
    "name": "CODHAB",
    "staff_id": 1436,
    "legal_advice_id": 5740,
    "created_at": "2017-01-16T11:20:24.447-02:00",
    "updated_at": "2017-01-16T11:20:24.447-02:00"
  },
  {
    "id": 141,
    "name": "CODHAB",
    "staff_id": 1436,
    "legal_advice_id": 5741,
    "created_at": "2017-01-18T10:44:05.148-02:00",
    "updated_at": "2017-01-18T10:44:05.148-02:00"
  },
  {
    "id": 142,
    "name": "CODHAB",
    "staff_id": 1436,
    "legal_advice_id": 5742,
    "created_at": "2017-01-18T10:46:51.293-02:00",
    "updated_at": "2017-01-18T10:46:51.293-02:00"
  },
  {
    "id": 143,
    "name": "CODHAB",
    "staff_id": 1436,
    "legal_advice_id": 5743,
    "created_at": "2017-01-18T11:02:51.878-02:00",
    "updated_at": "2017-01-18T11:02:51.878-02:00"
  },
  {
    "id": 144,
    "name": "JOHNNY CLEIK ROCHA DA SILVA",
    "staff_id": 1436,
    "legal_advice_id": 5744,
    "created_at": "2017-01-19T12:06:33.213-02:00",
    "updated_at": "2017-01-19T12:06:33.213-02:00"
  },
  {
    "id": 145,
    "name": "CODHAB",
    "staff_id": 1436,
    "legal_advice_id": 5745,
    "created_at": "2017-01-19T14:10:27.357-02:00",
    "updated_at": "2017-01-19T14:10:27.357-02:00"
  },
  {
    "id": 146,
    "name": "CODHAB",
    "staff_id": 1436,
    "legal_advice_id": 5746,
    "created_at": "2017-01-19T14:44:44.999-02:00",
    "updated_at": "2017-01-19T14:44:44.999-02:00"
  },
  {
    "id": 147,
    "name": "CODHAB",
    "staff_id": 1436,
    "legal_advice_id": 5747,
    "created_at": "2017-01-19T14:51:31.666-02:00",
    "updated_at": "2017-01-19T14:51:31.666-02:00"
  },
  {
    "id": 148,
    "name": "CODHAB",
    "staff_id": 1436,
    "legal_advice_id": 5748,
    "created_at": "2017-01-19T15:05:04.499-02:00",
    "updated_at": "2017-01-19T15:05:04.499-02:00"
  },
  {
    "id": 149,
    "name": "CODHAB",
    "staff_id": 1436,
    "legal_advice_id": 5749,
    "created_at": "2017-01-19T15:08:45.216-02:00",
    "updated_at": "2017-01-19T15:08:45.216-02:00"
  },
  {
    "id": 150,
    "name": "CODHAB",
    "staff_id": 1436,
    "legal_advice_id": 5750,
    "created_at": "2017-01-20T10:03:33.113-02:00",
    "updated_at": "2017-01-20T10:03:33.113-02:00"
  },
  {
    "id": 151,
    "name": "CODHAB",
    "staff_id": 1436,
    "legal_advice_id": 5751,
    "created_at": "2017-01-20T10:09:01.751-02:00",
    "updated_at": "2017-01-20T10:09:01.751-02:00"
  },
  {
    "id": 152,
    "name": "JOAO MEDEIROS SOUZA",
    "staff_id": 514,
    "legal_advice_id": 5773,
    "created_at": "2017-02-22T15:56:11.056-03:00",
    "updated_at": "2017-02-22T15:56:11.056-03:00"
  },
  {
    "id": 153,
    "name": "FAZENDA NACIONAL",
    "staff_id": 514,
    "legal_advice_id": 5796,
    "created_at": "2017-03-16T16:29:58.287-03:00",
    "updated_at": "2017-03-16T16:29:58.287-03:00"
  },
  {
    "id": 154,
    "name": "UNIAO",
    "staff_id": 514,
    "legal_advice_id": 5818,
    "created_at": "2017-04-04T09:34:57.041-03:00",
    "updated_at": "2017-04-04T09:34:57.041-03:00"
  },
  {
    "id": 155,
    "name": "PAULO ALVES BENTO",
    "staff_id": 514,
    "legal_advice_id": 5847,
    "created_at": "2017-05-02T10:00:40.294-03:00",
    "updated_at": "2017-05-02T10:00:40.294-03:00"
  },
  {
    "id": 156,
    "name": "GERCY MOREIRA DE JESUS COELHO",
    "staff_id": 514,
    "legal_advice_id": 5848,
    "created_at": "2017-05-02T10:02:49.565-03:00",
    "updated_at": "2017-05-02T10:02:49.565-03:00"
  },
  {
    "id": 157,
    "name": "MARCELO GERMANO DA SILVA",
    "staff_id": 514,
    "legal_advice_id": 5849,
    "created_at": "2017-05-02T10:06:01.236-03:00",
    "updated_at": "2017-05-02T10:06:01.236-03:00"
  },
  {
    "id": 158,
    "name": "EDNA MARIA JOSE BARBOSA",
    "staff_id": 514,
    "legal_advice_id": 5850,
    "created_at": "2017-05-02T10:11:39.651-03:00",
    "updated_at": "2017-05-02T10:11:39.651-03:00"
  },
  {
    "id": 159,
    "name": "ANA LUIZA PEREIRA FARINHA",
    "staff_id": 514,
    "legal_advice_id": 5868,
    "created_at": "2017-05-18T11:01:36.406-03:00",
    "updated_at": "2017-05-18T11:01:36.406-03:00"
  },
  {
    "id": 160,
    "name": "SANTINA MARIA DA CRUZ",
    "staff_id": 514,
    "legal_advice_id": 5876,
    "created_at": "2017-05-29T09:33:59.861-03:00",
    "updated_at": "2017-05-29T09:33:59.861-03:00"
  },
  {
    "id": 161,
    "name": "DANIEL DIAS MARQUES",
    "staff_id": 514,
    "legal_advice_id": 5917,
    "created_at": "2017-07-07T09:16:27.851-03:00",
    "updated_at": "2017-07-07T09:16:27.851-03:00"
  },
  {
    "id": 162,
    "name": "FRANCISCA CICERO MONTEIRO",
    "staff_id": 514,
    "legal_advice_id": 5959,
    "created_at": "2017-08-22T09:10:42.758-03:00",
    "updated_at": "2017-08-22T09:10:42.758-03:00"
  },
  {
    "id": 163,
    "name": "MANOEL ALVES DA SILVA",
    "staff_id": 514,
    "legal_advice_id": 5964,
    "created_at": "2017-08-25T14:40:20.335-03:00",
    "updated_at": "2017-08-25T14:40:20.335-03:00"
  },
  {
    "id": 164,
    "name": "JOSE FRANCISCO CALIXTO DE CALAIS E OUTRO",
    "staff_id": 514,
    "legal_advice_id": 5965,
    "created_at": "2017-08-25T14:41:57.636-03:00",
    "updated_at": "2017-08-25T14:41:57.636-03:00"
  },
  {
    "id": 165,
    "name": "LIVRARIA VISAO LTDA",
    "staff_id": 514,
    "legal_advice_id": 5970,
    "created_at": "2017-09-04T09:10:09.658-03:00",
    "updated_at": "2017-09-04T09:10:09.658-03:00"
  },
  {
    "id": 166,
    "name": "FRANCISCO RAIMUNDO DE ASSIS",
    "staff_id": 514,
    "legal_advice_id": 5986,
    "created_at": "2017-09-15T10:25:04.001-03:00",
    "updated_at": "2017-09-15T10:25:04.001-03:00"
  },
  {
    "id": 167,
    "name": "LUCIMAR LEANDRO PEIXOT E OUTRO",
    "staff_id": 514,
    "legal_advice_id": 5993,
    "created_at": "2017-09-25T18:39:45.023-03:00",
    "updated_at": "2017-09-25T18:39:45.023-03:00"
  },
  {
    "id": 168,
    "name": "TEREZA MARTINHA DA SILVA SANTOS",
    "staff_id": 514,
    "legal_advice_id": 6025,
    "created_at": "2017-10-24T08:57:48.918-02:00",
    "updated_at": "2017-10-24T08:57:48.918-02:00"
  },
  {
    "id": 169,
    "name": "OLIVEIRA MOREIRA DE LIMA",
    "staff_id": 514,
    "legal_advice_id": 6029,
    "created_at": "2017-10-26T10:06:18.503-02:00",
    "updated_at": "2017-10-26T10:06:18.503-02:00"
  },
  {
    "id": 170,
    "name": "CLAUDIO ROBERTO ALMEIDA RIBEIRO",
    "staff_id": 514,
    "legal_advice_id": 6273,
    "created_at": "2018-08-27T10:05:12.640-03:00",
    "updated_at": "2018-08-27T10:05:12.640-03:00"
  },
  {
    "id": 171,
    "name": "COSTA NOVAES CONSTRUÇÕES E EMPREENDIMENTOS LTDA",
    "staff_id": 514,
    "legal_advice_id": 6292,
    "created_at": "2018-09-27T11:11:31.780-03:00",
    "updated_at": "2018-09-27T11:11:31.780-03:00"
  },
  {
    "id": 172,
    "name": "ORLANDO FRANCISCO DA SILVA",
    "staff_id": 514,
    "legal_advice_id": 6302,
    "created_at": "2018-10-05T10:39:39.511-03:00",
    "updated_at": "2018-10-05T10:39:39.511-03:00"
  },
  {
    "id": 173,
    "name": "ANTENOR HERCULADO RODRIGUES",
    "staff_id": 514,
    "legal_advice_id": 6304,
    "created_at": "2018-10-10T10:51:59.517-03:00",
    "updated_at": "2018-10-10T10:51:59.517-03:00"
  },
  {
    "id": 174,
    "name": "JEFFERSON RODRIGUES FILHO",
    "staff_id": 514,
    "legal_advice_id": 218,
    "created_at": "2018-12-04T10:23:29.109-02:00",
    "updated_at": "2018-12-04T10:23:29.109-02:00"
  },
  {
    "id": 175,
    "name": "GENIVAL PEREIRA LEITE",
    "staff_id": 514,
    "legal_advice_id": 470,
    "created_at": "2018-12-04T10:28:50.500-02:00",
    "updated_at": "2018-12-04T10:28:50.500-02:00"
  },
  {
    "id": 176,
    "name": "JACQUELINE MACHADO DA SILVA",
    "staff_id": 514,
    "legal_advice_id": 6392,
    "created_at": "2019-03-08T15:54:16.237-03:00",
    "updated_at": "2019-03-08T15:54:16.237-03:00"
  },
  {
    "id": 177,
    "name": "AVILA CONSULTORIA ENGENHARIA E NCORPORAÇÃO LTDA",
    "staff_id": 514,
    "legal_advice_id": 6403,
    "created_at": "2019-03-27T11:06:57.199-03:00",
    "updated_at": "2019-03-27T11:06:57.199-03:00"
  }
]
